LICENSE
MANIFEST.in
README.rst
flask_mime.py
setup.cfg
setup.py
tox.ini
Flask_Mime.egg-info/PKG-INFO
Flask_Mime.egg-info/SOURCES.txt
Flask_Mime.egg-info/dependency_links.txt
Flask_Mime.egg-info/not-zip-safe
Flask_Mime.egg-info/requires.txt
Flask_Mime.egg-info/top_level.txt