Metadata-Version: 1.1
Name: Flask-Mime
Version: 0.1.0
Summary: Provides MIME type based request dispatching mechanism.
Home-page: https://github.com/lanius/flask-mime/
Author: lanius
Author-email: lanius@nirvake.org
License: Copyright (c) 2014 by lanius.
